rdcrm/__init__.py
rdcrm/customer.py
rdcrm/login.py
rdcrm/product.py
rdcrm/salesOrder.py
rdcrm/bill/__init__.py
rdcrm/bill/salesOrder.py
rdcrm/md/__init__.py
rdcrm/md/customer.py
rdcrm/md/product.py
rderp/__init__.py
rderp/apiAuth.py
rderp/billLinkModel.py
rderp/billModel.py
rderp/main.py
rderp/model.py
rderp/model_func.py
rderp/util.py
rderp/ar/__init__.py
rderp/ar/arReceivable.py
rderp/bill/__init__.py
rderp/md/__init__.py
rderp/md/customer.py
rderp/md/department.py
rderp/md/employee.py
rderp/md/material.py
rderp/md/materialCategory.py
rderp/md/operator.py
rderp/md/operatorGroup.py
rderp/md/permissisonObject.py
rderp/md/role.py
rderp/md/stock.py
rderp/md/supplier.py
rderp/md/unit.py
rderp/md/user.py
rderp/prd/__init__.py
rderp/prd/prdMoRpt.py
rderp/sales/__init__.py
rderp/sales/link2.py
rderp/sales/saleDeliveryNotice.py
rderp/sales/saleOrder.py
rderp/sales/saleOrder0.py
rderp/sales/saleOrderChange.py
rderp/sales/saleOutStock.py
rderp/sales/saleReturnNotice.py
rderp/sales/saleReturnStock.py
rderp/tax/__init__.py
rderp/tax/salesInvoice.py
rderp/tax/salesInvoiceVat.py
rderp/tax/salesInvoiceVot.py
rderp/tax/taxInvoice.py
rderp/wh/__init__.py
rderp/wh/stkMisDelivery.py
rderp/wh/stkMiscellaneous.py
rderp-2.4.1.dist-info/LICENSE
rderp-2.4.1.dist-info/METADATA
rderp-2.4.1.dist-info/WHEEL
rderp-2.4.1.dist-info/top_level.txt
rderp-2.4.1.dist-info/RECORD
